sum_num/__init__.py
sum_num/math_exp.py
sum_num-0.1.5.dist-info/LICENSE
sum_num-0.1.5.dist-info/METADATA
sum_num-0.1.5.dist-info/WHEEL
sum_num-0.1.5.dist-info/top_level.txt
sum_num-0.1.5.dist-info/RECORD
