Metadata-Version: 2.1
Name: sum-num
Version: 0.1.5
Summary: A package for addition and multiplication
Home-page: https://github.com/subhamyadav580/python-test-package
Author: Shubham Yadav
Author-email: subhamyadav580@gmail.com
Classifier: Programming Language :: Python :: 3
Classifier: License :: OSI Approved :: MIT License
Classifier: Operating System :: OS Independent
Requires-Python: >=3.6
License-File: LICENSE
